spektrum/__init__.py
spektrum/__main__.py
spektrum/exceptions.py
spektrum/expect.py
spektrum/logger.py
spektrum/runner.py
spektrum/spec.py
spektrum/utils.py
spektrum/reporting/__init__.py
spektrum/reporting/core.py
spektrum/reporting/data.py
spektrum/reporting/pretty.py
spektrum/reporting/testrail.py
spektrum/reporting/transport.py
spektrum/reporting/xunit.py
spektrum/vendor/__init__.py
spektrum/vendor/ast_decompiler.py
spektrum-1.2.1.dist-info/licenses/LICENSE
spektrum-1.2.1.dist-info/licenses/NOTICE
tests/__init__.py
tests/test_runner.py
tests/example_data/__init__.py
tests/example_data/case_dependencies.py
tests/example_data/example.py
tests/example_data/example_fixture.py
tests/example_data/select_module.py
tests/example_data/select_tests.py
spektrum-1.2.1.dist-info/METADATA
spektrum-1.2.1.dist-info/WHEEL
spektrum-1.2.1.dist-info/entry_points.txt
spektrum-1.2.1.dist-info/top_level.txt
spektrum-1.2.1.dist-info/RECORD
